tests
tutumcli
