Metadata-Version: 1.0
Name: tutum
Version: 0.14.0
Summary: CLI for Tutum
Home-page: http://www.tutum.co/
Author: Tutum, Inc.
Author-email: info@tutum.co
License: Apache v2
Keywords: tutum docker cli
Platform: UNKNOWN
